{
 "description": "Itatinga",
 "identifier": "http://w3.avignon.inra.fr/geonetwork_anaee/srv/eng/catalog.search#/metadata/4fbd2cb9-1a62-484b-8aa4-e2c94b8acf82",
 "language": "eng",
 "accessibility": "intellectualPropertyRights",
 "version": "N/A",
 "period": [
  "2008-01-01",
  "2008-01-01"
 ],
 "publisher": "N/A",
 "spatial": "N/A",
 "longitude": -48.7646,
 "latitude": -23.2045833,
 "license": "N/A",
 "citation": "N/A",
 "genre": [
  "structure"
 ],
 "creator": "N/A",
 "modification": "N/A",
 "distribution": "N/A",
 "image": "N/A",
 "thumbnail": "N/A",
 "headline": "no information",
 "abstract": "Le site d‚ÄôItatinga pr√©sente un dispositif d‚Äôexp√©rimentation √ long terme (d√©marrage en 2008), principalement sur des plantations d‚Äôeucalyptus. Les objectifs sont les suivants : - Comprendre le fonctionnement biog√©ochimiques de ces plantations d‚ÄôEucalyptus √ croissance rapide, et en particulier les couplages entre cycles de l‚Äôeau, du carbone, et des √©l√©ments nutritifs ; - Utiliser ces informations pour d√©velopper des mod√®les √©co-physiologiques simulant la croissance et les bilans hydriques, carbon√©s et en √©l√©ments min√©raux des plantations ; - Spatialiser les mod√®les √ partir de cartes du sol, d‚Äôimages satellitaires et de donn√©es m√©t√©orologiques ; - Evaluer l‚Äôimpact environnemental et la durabilit√© des plantations (impacts sur les ressources hydriques, sur la fertilit√© des sols, sur le climat r√©gional. Le dispositif se situe au Br√©sil, dans l‚ÄôEtat de Sao Paulo. Il se situe √ une altitude moyenne de 800 m. Longitude/latitude de 48¬∞43‚Äô40.60‚Äô‚ÄôO / 22¬∞58‚Äô4.50‚Äô‚ÄôS avec une temp√©rature moyenne annuelle de 19,6¬∞c et des pr√©cipitations de l‚Äôordre de 1350 mm/an. Le dispositif est sur un ferralsol constitu√© de 72% de sable, 15% d‚Äôargile, 3% de limon. Le site dispose d‚Äôune tour √ flux dans une plantation clonale d‚ÄôEucalyptus, o√π sont √©galement mesur√©s les cycles des √©l√©ments nutritifs mais √©galement des tests clonaux, de parcelles exp√©rimentales pour √©tudier les effets d‚Äôune exclusion partielle des pluies et de la fertilisation potassique sur les cycles des √©l√©ments min√©raux, du carbone et de l‚Äôeau, et enfin de parcelles exp√©rimentales comparant le fonctionnement √©cophysiologique/biog√©ochimique de plantations monosp√©cifiques et plurisp√©cifiques. Cette √©tude de l‚Äôimpact de la diversit√© arbor√©e sur le fonctionnement des √©cosyst√®me forestiers est men√©e sur des esp√®ces exotiques √ forte croissance (m√©lange d‚ÄôEucalyptus grandis et Acacia mangium) et sur des esp√®ces natives de la Mata Atl√¢ntica (biome dans lequel se situe le site d‚ÄôItatinga). Th√©matiques abord√©es : Biog√©ochimie des plantations foresti√®res, Intensification √©cologique des plantations foresti√®res tropicales.",
 "category": "structure",
 "created": "N/A",
 "credit": "N/A",
 "published": "2010-12-08",
 "producer": "./resources/codeList.xml#CI_RoleCode",
 "author": [
  "AnaEE-France Locations"
 ],
 "space": "N/A",
 "url": "N/A",
 "temporal": [
  "2008-01-01",
  "2008-01-01"
 ],
 "sponsor": "N/A",
 "size": 50000,
 "similar": "N/A",
 "publication": "Commission Regulation (EU) No 1089/2010 of 23 November 2010 implementing Directive 2007/2/EC of the European Parliament and of the Council as regards interoperability of spatial data sets and services",
 "provider": "N/A",
 "position": "N/A",
 "name": "inapplicable",
 "measurement": "N/A",
 "material": "N/A",
 "maintainer": "N/A",
 "location": "N/A",
 "issn": "N/A",
 "is Part Of": "N/A",
 "is Based On": "N/A",
 "free": "N/A",
 "included": "N/A",
 "editor": "N/A",
 "editEIDR": "N/A",
 "copyright Year": "N/A",
 "copyright Notice": "N/A",
 "copyright Holder": "N/A",
 "contributor": "N/A",
 "content Reference Time": "N/A",
 "character": "N/A",
 "acquire License Page": "N/A",
 "access": "N/A",
 "about": "N/A",
 "rights": "N/A",
 "relation": "N/A",
 "attribution": "N/A",
 "previous": "N/A",
 "referenced": "N/A",
 "series": "N/A",
 "policy": "intellectualPropertyRights",
 "current": "N/A",
 "constraints": "N/A",
 "status": "N/A",
 "spatialRepresentationType": "N/A",
 "spatialRepresentationInfo": "N/A",
 "scope": "N/A",
 "party": "N/A",
 "releasability": "N/A",
 "reference": "N/A",
 "purpose": "N/A",
 "locale": "N/A",
 "metadata Profile": "ISO 19115:2003/19139",
 "metadata Linkage": "N/A",
 "metadata Identifier": "N/A",
 "MD LegalConstraints": "N/A",
 "MD Identification": "N/A",
 "environment Description": "N/A",
 "distributor": "N/A",
 "quality": "N/A",
 "info": [
  "tation",
  "Interaction diversity",
  "Species distributions",
  "litterfall",
  "sortant",
  "Trait diversity",
  "plantation",
  "respiration",
  "rature",
  "radiation",
  "rayonnement",
  "plant"
 ],
 "contact": null,
 "accountablePerson": [
  "Joann√®s Guillemot"
 ],
 "landing_page": "N/A",
 "keywords": [
  "surface terri√®re",
  "rayonnement PAR sous couvert vegetal",
  "rayonnement sortant",
  "direction du vent",
  "diffuse global radiation",
  "flux de s√®ve",
  "air temperature",
  "gmd:PT_FreeText_PropertyType",
  "PAR below vegetation cover",
  "photosynthetically active radiation",
  "vegetation mineralomass",
  "rayonnement global",
  "soil granulometry",
  "aerial biomass",
  "theme",
  "r√©flectance spectrale (NDVI ‚Ä¶)",
  "dry bulk density of soil",
  "eucalyptus plantation",
  "biomasse racinaire",
  "soil moisture",
  "plant trait",
  "vegetation growth",
  "precipitation",
  "soil temperature",
  "transmitted radiation",
  "min√©ralomasse de la v√©g√©tation",
  "dendrom√©trie",
  "plantation d'eucalyptus",
  "indice foliaire",
  "vegetation height",
  "teneur en azote de la v√©g√©tation",
  "Environmental monitoring facilities",
  "vegetation carbon dioxide profile",
  "vegetation nitrogen content",
  "granulom√©trie du sol",
  "stock d'√©l√©ments dans la liti√®re",
  "rayonnement atmosph√©rique",
  "publication",
  "spectral reflectance (NDVI ‚Ä¶)",
  "litti√®re",
  "air humidity",
  "energy flux in soil vegetation atmosphere system",
  "respiration du sol",
  "temp√©rature du sol",
  "temp√©rature de l'air dans la v√©g√©tation",
  "net radiation",
  "Itatinga",
  "pluviolessivat",
  "biomasse microbienne",
  "air temperature in vegetation",
  "AnaEE-France Locations",
  "flux de carbone dans le syst√®me sol v√©g√©tation atmosph√®re",
  "litter",
  "vitesse du vent",
  "rayonnement transmis",
  "atmospheric radiation",
  "place",
  "microbial diversity",
  "age de la v√©g√©tation",
  "vegetation age",
  "vegetation water vapour profile",
  "throughfall",
  "dendrometry",
  "rayonnement r√©fl√©chi",
  "fertilisation",
  "pluviom√©trie",
  "litterfall flow",
  "densit√© apparente du sol",
  "root biomass",
  "croissance de la v√©gt√©tation",
  "flux d'√©nergie dans le syst√®me sol v√©g√©tation atmosph√®re",
  "sap flow",
  "wind direction",
  "elements stock in litter",
  "basal area",
  "plant respiration",
  "sensible heat flux",
  "carbon dioxide flux",
  "microbial biomass",
  "profil de vapeur d'eau dans la v√©g√©tation",
  "vegetation carbon content",
  "foliar index",
  "outgoing radiation",
  "rayonnement net",
  "humidit√© de l'air",
  "tree species",
  "Installations de suivi environnemental",
  "carbon flux in soil vegetation atmosphere system",
  "flux de retomb√©e de liti√®re a√©rienne",
  "rotation",
  "traits des plantes",
  "global radiation",
  "wind velocity",
  "profil du dioxyde de carbone dans la v√©g√©tation",
  "teneur en carbone de la v√©g√©tation",
  "pluviometry",
  "esp√®ces d'arbre",
  "hauteur de la v√©g√©tation",
  "respiration de la plante",
  "evapotranspiration",
  "chute de liti√®re",
  "temp√©rature de l'air",
  "reflected radiation",
  "rayonnement global diffus",
  "litterfall",
  "humidit√© du sol",
  "√©vapotranspiration",
  "diversit√© microbienne",
  "biomasse a√©rienne",
  "AnaEE-France",
  "flux de dioxyde de carbone",
  "pr√©cipitation",
  "soil respiration"
 ]
}