{
  "coverageGeo": {
    "coordinates": [19.7745, 64.25611, 267.0],
    "type": "Point"
  },
  "fileName": "SE-Svb_BM_20210404_L04_F01.dat",
  "hash": "mTiNFoOnD_QXv2IYiTygxcMVjINC1q03nzjQmkQxqXA",
  "parentCollections": [],
  "pid": "11676/mTiNFoOnD_QXv2IYiTygxcMV",
  "references": {
    "acknowledgements": ["Work was funded by grant National Research Infrastructure ICOS Sweden (2019-00205) from Swedish Research Council"],
    "authors": [{
      "firstName": "Matthias",
      "lastName": "Peichl",
      "self": {
        "comments": [],
        "uri": "http://meta.icos-cp.eu/resources/people/Matthias_Peichl"
      }
    }, {
      "firstName": "Mats",
      "lastName": "Nilsson",
      "self": {
        "comments": [],
        "uri": "http://meta.icos-cp.eu/resources/people/Mats%20B._Nilsson"
      }
    }, {
      "firstName": "Paul",
      "lastName": "Smith",
      "orcid": "0000-0002-3773-1419",
      "self": {
        "comments": [],
        "uri": "http://meta.icos-cp.eu/resources/people/Paul_Smith"
      }
    }, {
      "firstName": "Per",
      "lastName": "Marklund",
      "orcid": "0000-0001-7264-5498",
      "self": {
        "comments": [],
        "uri": "http://meta.icos-cp.eu/resources/people/Per_Marklund"
      }
    }, {
      "firstName": "Giuseppe",
      "lastName": "De Simon",
      "self": {
        "comments": [],
        "uri": "http://meta.icos-cp.eu/resources/people/Giuseppe_De%20Simon"
      }
    }, {
      "firstName": "Pernilla",
      "lastName": "Löfvenius",
      "self": {
        "comments": [],
        "uri": "http://meta.icos-cp.eu/resources/people/Pernilla_L%C3%B6fvenius"
      }
    }, {
      "firstName": "Rowan",
      "lastName": "Dignam",
      "self": {
        "comments": [],
        "uri": "http://meta.icos-cp.eu/resources/people/Rowan_Dignam"
      }
    }, {
      "firstName": "Jutta",
      "lastName": "Holst",
      "self": {
        "comments": [],
        "uri": "http://meta.icos-cp.eu/resources/people/Jutta_Holst"
      }
    }, {
      "firstName": "Meelis",
      "lastName": "Mölder",
      "orcid": "0000-0001-6767-3195",
      "self": {
        "comments": [],
        "uri": "http://meta.icos-cp.eu/resources/people/Meelis_M%C3%B6lder"
      }
    }, {
      "firstName": "Tommy",
      "lastName": "Andersson",
      "self": {
        "comments": [],
        "uri": "http://meta.icos-cp.eu/resources/people/Tommy_Andersson"
      }
    }, {
      "firstName": "Kim",
      "lastName": "Lindgren",
      "self": {
        "comments": [],
        "uri": "http://meta.icos-cp.eu/resources/people/Kim_Lindgren"
      }
    }, {
      "firstName": "Mats",
      "lastName": "Öquist",
      "self": {
        "comments": [],
        "uri": "http://meta.icos-cp.eu/resources/people/Mats_%C3%96quist"
      }
    }],
    "citationBibTex": "@misc{https://hdl.handle.net/11676/mTiNFoOnD_QXv2IYiTygxcMV,\r\n  author={Peichl, M., Nilsson, M., Smith, P., Marklund, P., De Simon, G., Löfvenius, P., Dignam, R., Holst, J., Mölder, M., Andersson, T., Lindgren, K., Öquist, M.},\r\n  title={ICOS ETC Bio Meteo Raw ASCII, Svartberget, 2021-04-04},\r\n  year={2021},\r\n  url={https://hdl.handle.net/11676/mTiNFoOnD_QXv2IYiTygxcMV},\r\n  publisher={Svartberget},\r\n  copyright={https://creativecommons.org/licenses/by/4.0/},\r\n  pid={11676/mTiNFoOnD_QXv2IYiTygxcMV}\r\n}",
    "citationRis": "TY - DATA\r\nT1 - ICOS ETC Bio Meteo Raw ASCII, Svartberget, 2021-04-04\r\nID - 11676/mTiNFoOnD_QXv2IYiTygxcMV\r\nPY - 2021\r\nUR - https://hdl.handle.net/11676/mTiNFoOnD_QXv2IYiTygxcMV\r\nPB - Svartberget\r\nAU - Peichl, M.\r\nAU - Nilsson, M.\r\nAU - Smith, P.\r\nAU - Marklund, P.\r\nAU - De Simon, G.\r\nAU - Löfvenius, P.\r\nAU - Dignam, R.\r\nAU - Holst, J.\r\nAU - Mölder, M.\r\nAU - Andersson, T.\r\nAU - Lindgren, K.\r\nAU - Öquist, M.\r\nER - ",
    "citationString": "Peichl, M., Nilsson, M., Smith, P., Marklund, P., De Simon, G., Löfvenius, P., Dignam, R., Holst, J., Mölder, M., Andersson, T., Lindgren, K., Öquist, M., ICOS RI, 2021. ICOS ETC Bio Meteo Raw ASCII, Svartberget, 2021-04-04, https://hdl.handle.net/11676/mTiNFoOnD_QXv2IYiTygxcMV",
    "temporalCoverageDisplay": "2021-04-04"
  },
  "size": 1047630,
  "specificInfo": {
    "acquisition": {
      "instrument": {
        "comments": [],
        "label": "DL-Campbell CR800",
        "uri": "http://meta.icos-cp.eu/resources/instruments/ETC_58_4"
      },
      "interval": {
        "start": "2021-04-03T23:00:00Z",
        "stop": "2021-04-04T23:00:00Z"
      },
      "station": {
        "coverage": {
          "alt": 267.0,
          "geo": {
            "coordinates": [19.7745, 64.25611, 267.0],
            "type": "Point"
          },
          "label": "SE-Svb",
          "lat": 64.25611,
          "lon": 19.7745
        },
        "funding": [{
          "awardNumber": "2015-06020",
          "awardTitle": "National Research Infrastructure ICOS Sweden",
          "awardUrl": "www.icos-sweden.se",
          "funder": {
            "org": {
              "name": "Swedish Research Council",
              "self": {
                "comments": [],
                "uri": "http://meta.icos-cp.eu/resources/organizations/Swedish%20Research%20Council"
              }
            }
          },
          "self": {
            "comments": ["co-financed by Lund University, Gothenburg University, Swedish Polar Research Secretariat, SLU, Stockholm University and Uppsala University"],
            "label": "National Research Infrastructure ICOS Sweden to Svartberget",
            "uri": "http://meta.icos-cp.eu/resources/fundings/58_2015-06020"
          },
          "start": "2016-04-01",
          "stop": "2020-12-31"
        }, {
          "awardNumber": "2019-00205",
          "awardTitle": "National Research Infrastructure ICOS Sweden",
          "awardUrl": "www.icos-sweden.se",
          "funder": {
            "org": {
              "name": "Swedish Research Council",
              "self": {
                "comments": [],
                "uri": "http://meta.icos-cp.eu/resources/organizations/Swedish%20Research%20Council"
              }
            }
          },
          "self": {
            "comments": ["co-financed by Lund University, SLU, Gothenburg University, Swedish Polar Research Secretariat, Uppsala University and SMHI"],
            "label": "National Research Infrastructure ICOS Sweden to Svartberget",
            "uri": "http://meta.icos-cp.eu/resources/fundings/58_2019-00205"
          },
          "start": "2021-01-01",
          "stop": "2024-12-31"
        }],
        "id": "SE-Svb",
        "org": {
          "name": "Svartberget",
          "self": {
            "comments": ["The station Svartberget, with ICOS code SE-Svb, is located about 70 km west of the Gulf of Bothnia, NW of the city Umeå. The site in a northern Sweden boreal forest in a landscape characterized by the ridges, valleys and lakes stretching from northwest to southeast, and the station is located within the Svartberget Experimental forest, about 1520 hectare forest land with forest research activities since 1909."],
            "label": "SE-Svb",
            "uri": "http://meta.icos-cp.eu/resources/stations/ES_SE-Svb"
          }
        },
        "pictures": ["https://fileshare.icos-cp.eu/s/XJDPj6KSRFWdbtB/preview"],
        "specificInfo": {
          "_type": "etc",
          "climateZone": {
            "comments": [],
            "label": "Subacrtic (Dfc)",
            "uri": "http://meta.icos-cp.eu/ontologies/cpmeta/koppen_Dfc"
          },
          "countryCode": "SE",
          "documentation": [{
            "hash": "MLKNuIcTWUo1dRDAFvTK_C_NRrezaGfQ7ylc6jrHEa0",
            "name": "SE-Svb ICOS Ecosystem Station Labelling Report.pdf",
            "res": "https://meta.icos-cp.eu/objects/MLKNuIcTWUo1dRDAFvTK_C_N"
          }],
          "ecosystemType": {
            "comments": ["Lands dominated by woody vegetation with a percent cover >60% and height exceeding 2 meters. Almost all trees remain green all year. Canopy is never without green foliage."],
            "label": "Evergreen Needleleaf Forests",
            "uri": "http://meta.icos-cp.eu/ontologies/cpmeta/igbp_ENF"
          },
          "labelingDate": "2019-04-29",
          "meanAnnualPrecip": 614.0,
          "meanAnnualRad": 93.4,
          "meanAnnualTemp": 1.8,
          "stationClass": "2",
          "stationDocs": [],
          "stationPubs": [],
          "theme": {
            "icon": "https://static.icos-cp.eu/images/themes/eco.svg",
            "markerIcon": "https://static.icos-cp.eu/share/stations/icons/es.png",
            "self": {
              "comments": [],
              "label": "Ecosystem data",
              "uri": "http://meta.icos-cp.eu/resources/themes/ecosystem"
            }
          },
          "timeZoneOffset": 1
        }
      }
    }
  },
  "specification": {
    "dataLevel": 0,
    "documentation": [],
    "encoding": {
      "comments": [],
      "label": "plain file",
      "uri": "http://meta.icos-cp.eu/ontologies/cpmeta/plainFileEncoding"
    },
    "format": {
      "comments": [],
      "label": "Raw ASCII ETC station data",
      "uri": "http://meta.icos-cp.eu/ontologies/cpmeta/asciiEtcRawTimeSer"
    },
    "project": {
      "keywords": ["ICOS"],
      "self": {
        "comments": ["Official ICOS data"],
        "label": "ICOS",
        "uri": "http://meta.icos-cp.eu/resources/projects/icos"
      }
    },
    "self": {
      "comments": [],
      "label": "ICOS ETC Bio Meteo Raw ASCII",
      "uri": "http://meta.icos-cp.eu/resources/cpmeta/etcBioMeteoRawSeriesCsv"
    },
    "theme": {
      "icon": "https://static.icos-cp.eu/images/themes/eco.svg",
      "markerIcon": "https://static.icos-cp.eu/share/stations/icons/es.png",
      "self": {
        "comments": [],
        "label": "Ecosystem data",
        "uri": "http://meta.icos-cp.eu/resources/themes/ecosystem"
      }
    }
  },
  "submission": {
    "start": "2021-04-05T02:31:17.090Z",
    "stop": "2021-04-05T02:31:19.175Z",
    "submitter": {
      "name": "Svartberget",
      "self": {
        "comments": ["The station Svartberget, with ICOS code SE-Svb, is located about 70 km west of the Gulf of Bothnia, NW of the city Umeå. The site in a northern Sweden boreal forest in a landscape characterized by the ridges, valleys and lakes stretching from northwest to southeast, and the station is located within the Svartberget Experimental forest, about 1520 hectare forest land with forest research activities since 1909."],
        "label": "SE-Svb",
        "uri": "http://meta.icos-cp.eu/resources/stations/ES_SE-Svb"
      }
    }
  }
}